wappsto/__init__.py
wappsto/status.py
wappsto/connection/__init__.py
wappsto/connection/communication.py
wappsto/connection/event_storage.py
wappsto/connection/message_data.py
wappsto/connection/receive_data.py
wappsto/connection/seluxit_rpc.py
wappsto/connection/send_data.py
wappsto/data_operation/__init__.py
wappsto/data_operation/data_manager.py
wappsto/data_operation/decoder.py
wappsto/data_operation/encoder.py
wappsto/errors/__init__.py
wappsto/errors/wappsto_errors.py
wappsto/modules/__init__.py
wappsto/modules/device.py
wappsto/modules/network.py
wappsto/modules/state.py
wappsto/modules/value.py
wappsto-1.2.12.dist-info/LICENSE
wappsto-1.2.12.dist-info/METADATA
wappsto-1.2.12.dist-info/WHEEL
wappsto-1.2.12.dist-info/top_level.txt
wappsto-1.2.12.dist-info/RECORD
