Metadata-Version: 2.1
Name: wappsto
Version: 1.2.12
Summary: Python Package to connect to wappsto.com
Home-page: https://github.com/wappsto/wappsto-python
Author: Seluxit A/S
Author-email: support@seluxit.com
License: Apache-2.0
Classifier: Programming Language :: Python :: 3
Classifier: Operating System :: OS Independent
Requires-Python: >3.4.0
License-File: LICENSE
Requires-Dist: jsonrpcclient (==3.3.6)
